tester_laboratorio2.v
module tester_laboratorio2(
    output reg clk,
    output reg reset,
    output reg tarjeta_recibida,
    output reg tipo_de_tarjeta,
    output reg [15:0] pin,
    output reg [4:0]digito,
    output reg digito_stb,
    output reg tipo_trans,
    output reg [31:0] monto,
    output reg monto_stb,

    input balance_actualizado,
    input entregar_dinero,
    input fondos_insuficientes,
    input pin_incorrecto,
    input bloqueo,
    input advertencia
);

parameter h_freq = 1;
//definición de media frecuencia en unidades de tiempo
//acá definimos el clk
always begin
   #h_freq clk = !clk;
end

//iniciamos las pruebas
initial begin
    clk = 0;
    reset = 0;
    tarjeta_recibida = 0;
    tipo_trans = 0;
    monto_stb = 0;
    pin = 15'b0;
    digito = 4'b0;
    monto = 31'b0;

    //se inicia el cajero
    #1 reset = 1;
    #1 reset = 0;
    tarjeta_recibida = 1;
    tipo_de_tarjeta = 0;
    pin = 'h3443;

    //primer caso: pin acertado + depósito
    //prueba 1: se detecta que la tarjeta sea del bcr
    //tipo_de_tarjeta = 0;

    //prueba 2: se ingresan los digitos del pin
    //primer dígito
    #3 digito = 3;
    #2 digito_stb = 1;
    #2 digito_stb = 0;
    digito = 0;

    //segundo dígito
    #3 digito = 4;
    #2 digito_stb = 1;
    #2 digito_stb = 0;
    digito = 0;

    //tercer dígito
    #3 digito = 4;
    #2 digito_stb = 1;
    #2 digito_stb = 0;
    digito = 0;

    //cuarto dígito 
    #3 digito = 3;
    #2 digito_stb = 1;
    #2 digito_stb = 0;
    digito = 0;

    //prueba 3: se hace un depósito
    //tipo_trans = 0;

    //se ingresa el monto a depositar
    /*#3 monto = 100;
    #1 monto_stb = 1;
    #1 monto_stb =0;
    monto = 0;*/
    #10;

    //se prueba el primer pin
    //se ingresa el primer dígito
    /*#3 digito = 1;
    #1 digito_stb = 1;
    #1 digito_stb = 0;
    digito = 0;

    //segundo dígito
    #3 digito = 2;
    #1 digito_stb = 1;
    #1 digito_stb = 0;
    digito = 0;

    //tercer dígito
    #3 digito = 3;
    #1 digito_stb = 1;
    #1 digito_stb = 0;
    digito = 0;

    //cuarto dígito
    #3 digito = 4;
    #1 digito_stb = 1;
    #1 digito_stb = 0;
    digito = 0;

    //se ingresa el segundo pin
    #3 digito = 1;
    #1 digito_stb = 1;
    #1 digito_stb = 0;
    digito = 0;

    //segundo dígito
    #3 digito = 1;
    #1 digito_stb = 1;
    #1 digito_stb = 0;
    digito = 0;

    //tercer dígito
    #3 digito = 1;
    #1 digito_stb = 1;
    #1 digito_stb = 0;
    digito = 0;

    //cuarto dígito
    #3 digito = 1;
    #1 digito_stb = 1;
    #1 digito_stb = 0;
    digito = 0;

    //tercer pin
    #3 digito = 0;
    #1 digito_stb = 1;
    #1 digito_stb = 0;
    digito = 0;

    //segundo dígito
    #3 digito = 0;
    #1 digito_stb = 1;
    #1 digito_stb = 0;
    digito = 0;

    //tercer dígito
    #3 digito = 0;
    #1 digito_stb = 1;
    #1 digito_stb = 0;
    digito = 0;

    //cuarto dígito
    #3 digito = 0;
    #1 digito_stb = 1;
    #1 digito_stb = 0;
    digito = 0;

    //se bloquea el cajero y se reinicia
    #5 reset = 0;
    #5 reset = 1;

    //se ingresa el pin verdadero
    #3 digito = 2;
    #1 digito_stb = 1;
    #1 digito_stb = 0;
    digito = 0;

    //segundo dígito
    #3 digito = 0;
    #1 digito_stb = 1;
    #1 digito_stb = 0;
    digito = 0;

    //tercer dígito
    #3 digito = 2;
    #1 digito_stb = 1;
    #1 digito_stb = 0;
    digito = 0;

    //cuarto dígito
    #3 digito = 3;
    #1 digito_stb = 1;
    #1 digito_stb = 0;
    digito = 0;
    //se autentica el usuario

    //se prueba el depósito
    tipo_trans = 0;

    //se ingresa el monto a depositar
    #3 monto = 100000;
    #1 monto_stb = 1;
    monto_stb = 0;
    monto = 0;

    //se prueba el retiro
    #5 tipo_trans = 0;

    //se reinicia el cajero
    #5 reset = 0;
    #5 reset = 1;

    //se ingresa el pin correcto
    #3 digito = 2;
    #1 digito_stb = 1;
    #1 digito_stb = 0;
    digito = 0;

    //segundo dígito
    #3 digito = 0;
    #1 digito_stb = 1;
    #1 digito_stb = 0;
    digito = 0;

    //tercer dígito
    #3 digito = 2;
    #1 digito_stb = 1;
    #1 digito_stb = 0;
    digito = 0;

    //cuarto dígito
    #3 digito = 3;
    #1 digito_stb = 1;
    #1 digito_stb = 0;
    digito = 0;

    //se intenta un retiro con fondos insuficientes
    #3 monto = 1000000000;
    #1 monto_stb = 1;
    #1 monto_stb = 0;
    monto = 0;

    //se vuelve a ingresar el usuario y se reinicia el cajero con el tipo de transacción
    #5 tipo_trans = 1;
    #5 reset = 0;
    #5 reset = 1;

    //ingreso del código
    #3 digito = 2;
    #1 digito_stb = 1;
    #1 digito_stb = 0;
    digito = 0;

    //segundo dígito
    #3 digito = 0;
    #1 digito_stb = 1;
    #1 digito_stb = 0;
    digito = 0;

    //tercer dígito
    #3 digito = 2;
    #1 digito_stb = 1;
    #1 digito_stb = 0;
    digito = 0;

    //cuarto dígito
    #3 digito = 3;
    #1 digito_stb = 1;
    #1 digito_stb = 0;
    digito = 0;
    //se autentica el usuario y se procede con la transacción
    #3 monto = 9100;
    #1 monto_stb = 1;
    #1 monto_stb = 0;
    monto = 0;

    #10;*/
    $finish;
end
endmodule

laboratorio2.v
module laboratorio2(
  input clk,
  input reset,
  input tarjeta_recibida,
  input tipo_de_tarjeta,
  input [15:0] pin,
  input [4:0] digito,
  input digito_stb, //se pone en alto durante un ciclo de reloj cuando se presiona una tecla
  input tipo_trans,
  input [31:0] monto,
  input monto_stb,

  output reg balance_actualizado,
  output reg entregar_dinero,
  output reg fondos_insuficientes,
  output reg pin_incorrecto,
  output reg bloqueo,
  output reg advertencia
  /*output reg tipo_de_tarjeta*/
);
  //variables internas
  reg [63:0] balance;
  reg [2:0] contador_pin;//cuenta los digitos del pin ingresados al sistema
  reg [15:0] pin_usuario; //pin que digita el usuario
  reg [1:0] intentos_pin;

  //variables de estados
  reg [5:0] state;
  reg [5:0] next_state;
  
  //definimos los estados como parámetros
  parameter esperando_tarjeta = 0; //default
  parameter esperando_pin = 1;
  parameter usuario_identificado = 2;
  parameter deposito = 3;
  parameter retiro = 4;
  parameter bloqueado = 5;

  always @(posedge clk) begin
    if (!reset)begin
      next_state <= esperando_tarjeta;
    end
    else begin
      state <= next_state;
    end
  end

  always @(*)begin
    case(state)

      //estado inicial: esperando tarjeta
      esperando_tarjeta:
      begin
        if(tarjeta_recibida == 1) begin
        //Cuando se ingresa una tarjeta que no es del bcr, tipo_de_tarjeta se pone en y se cobra una comisión
          if (tipo_de_tarjeta == 1) begin
            balance = balance - 1000;
            next_state = esperando_tarjeta;
            //como en la vida real, se descuenta la comisión y se pasa a pedir el pin
          end

          else begin
            //en el caso de que la tarjeta sí es bcr, no se cobra la comision y se procede.
            balance_actualizado = 0;
            entregar_dinero = 0;
            fondos_insuficientes = 0;
            pin_incorrecto = 0;
            bloqueo = 0;
            advertencia = 0;
            contador_pin = 0;
            pin_usuario = 0;
            intentos_pin = 0;
            //balance = 1000000;
            next_state = esperando_pin;//pin acertado + deposito
          end
        end
        else begin
          //si no, se queda esperando la tarjeta
          next_state = esperando_tarjeta;
          balance <= 0;
        end
      end

      //primer estado
      esperando_pin:
      begin
        if(digito_stb) begin
          pin_usuario = {pin_usuario, digito};
          contador_pin = contador_pin + 1;

          next_state = esperando_pin; //se vuelve a esperando_pin para esperar el siguiente dígito
        end
        else begin
          //mientras digito_stb esté en cero se mantendrá esperando el ingreso del digito
          next_state = esperando_pin;
        end

        //una vez que se ingresó el pin, se verifica si es válido o no
        if(contador_pin == 4) begin
          if(pin_usuario == pin)begin
            //el pin ingresado es el correcto y se identifica el usuario
            pin_usuario = 0;
            contador_pin = 0; //se reinicia el contador
            next_state = usuario_identificado;
          end
          else begin
            contador_pin = 0;
            intentos_pin = intentos_pin + 1;
            pin_incorrecto = 1; //se ingresa el pin incorrecto una vez

            if(intentos_pin == 2)begin
              advertencia = 1;
              next_state = esperando_pin;
            end
            else if(intentos_pin == 3) 
              next_state = bloqueado;
            else
              next_state = esperando_pin;
          end
        end
        else begin
          next_state = esperando_pin; //se ingresa el pin incorrecto una vez
        end
      end

      //segundo estado
      usuario_identificado:
      begin
        //una vez que se identifica el usuario, se define el tipo de transacción
        if(tipo_trans) 
          next_state = retiro;
        else
          next_state = deposito;
      end

      //tercer estado
      deposito:
      begin
        if (monto_stb) begin
          //se le suma el monto depositado al balance de la cuenta
          balance = balance + monto;
          balance_actualizado = 1;
          //se vuelve a esperar a que se ingrese el pin
          next_state = esperando_tarjeta;
        end
        /*else begin
          next_state = esperando_pin;
        end*/
      end

      // cuarto estado
      retiro:
      begin
        if (monto_stb) begin
          if (balance > monto) begin
            balance = balance + -monto;
            balance_actualizado = 1;
            entregar_dinero = 1;
            next_state = esperando_tarjeta;
          end
          else begin
            fondos_insuficientes = 1;
            next_state = esperando_tarjeta;
          end
        end
        /*else begin
          next_state = retiro;
        end*/
      end

      //quinto estado
      bloqueado:
      begin
        //cuando se bloquea la tarjeta, se mantiene bloqueada
        bloqueo = 1;
        next_state = bloqueado;
      end

      //estado default
      default:
      begin
        next_state = esperando_tarjeta;
      end      
    endcase
  end
endmodule

laboratorio2_testbench.v
`include "laboratorio2.v"
`include "tester_laboratorio2.v"

module laboratorio2_testbench;
//wires del testbench
wire clk, reset;
wire tarjeta_recibida, tipo_de_tarjeta;
wire [15:0] pin;
wire [4:0] digito;
wire digito_stb;
wire [31:0] monto;
wire tipo_trans, monto_stb;
wire balance_actualizado, entregar_dinero,fondos_insuficientes;
wire pin_incorrecto, bloqueo, advertencia;

laboratorio2 DUT(
    .clk(clk),
    .reset(reset),
    .tarjeta_recibida(tarjeta_recibida),
    .tipo_de_tarjeta(tipo_de_tarjeta),
    .pin(pin[15:0]),
    .digito(digito[4:0]),
    .digito_stb(digito_stb),
    .tipo_trans(tipo_trans),
    .monto(monto[31:0]),
    .monto_stb(monto_stb),
    .balance_actualizado(balance_actualizado),
    .entregar_dinero(entregar_dinero),
    .fondos_insuficientes(fondos_insuficientes),
    .pin_incorrecto(pin_incorrecto),
    .bloqueo(bloqueo),
    .advertencia(advertencia)
);

tester_laboratorio2 test(
    .clk(clk),
    .reset(reset),
    .tarjeta_recibida(tarjeta_recibida),
    .tipo_de_tarjeta(tipo_de_tarjeta),
    .pin(pin[15:0]),
    .digito(digito[4:0]),
    .digito_stb(digito_stb),
    .tipo_trans(tipo_trans),
    .monto(monto[31:0]),
    .monto_stb(monto_stb),
    .balance_actualizado(balance_actualizado),
    .entregar_dinero(entregar_dinero),
    .fondos_insuficientes(fondos_insuficientes),
    .pin_incorrecto(pin_incorrecto),
    .bloqueo(bloqueo),
    .advertencia(advertencia)
);

//se monitorea la actividad de las pruebas
initial begin
    $dumpfile("tb.vcd");
    $dumpvars;
end
endmodule

tb.vcd
$date
	Fri May 17 02:51:02 2024
$end
$version
	Icarus Verilog
$end
$timescale
	1s
$end
$scope module laboratorio2_testbench $end
$var wire 1 ! tipo_trans $end
$var wire 1 " tipo_de_tarjeta $end
$var wire 1 # tarjeta_recibida $end
$var wire 1 $ reset $end
$var wire 1 % pin_incorrecto $end
$var wire 16 & pin [15:0] $end
$var wire 1 ' monto_stb $end
$var wire 32 ( monto [31:0] $end
$var wire 1 ) fondos_insuficientes $end
$var wire 1 * entregar_dinero $end
$var wire 1 + digito_stb $end
$var wire 5 , digito [4:0] $end
$var wire 1 - clk $end
$var wire 1 . bloqueo $end
$var wire 1 / balance_actualizado $end
$var wire 1 0 advertencia $end
$scope module DUT $end
$var wire 1 ! tipo_trans $end
$var wire 1 " tipo_de_tarjeta $end
$var wire 1 # tarjeta_recibida $end
$var wire 1 $ reset $end
$var wire 16 1 pin [15:0] $end
$var wire 1 ' monto_stb $end
$var wire 32 2 monto [31:0] $end
$var wire 1 + digito_stb $end
$var wire 5 3 digito [4:0] $end
$var wire 1 - clk $end
$var reg 1 0 advertencia $end
$var reg 64 4 balance [63:0] $end
$var reg 1 / balance_actualizado $end
$var reg 1 . bloqueo $end
$var reg 3 5 contador_pin [2:0] $end
$var reg 1 * entregar_dinero $end
$var reg 1 ) fondos_insuficientes $end
$var reg 2 6 intentos_pin [1:0] $end
$var reg 6 7 next_state [5:0] $end
$var reg 1 % pin_incorrecto $end
$var reg 16 8 pin_usuario [15:0] $end
$var reg 6 9 state [5:0] $end
$upscope $end
$scope module test $end
$var wire 1 0 advertencia $end
$var wire 1 / balance_actualizado $end
$var wire 1 . bloqueo $end
$var wire 1 * entregar_dinero $end
$var wire 1 ) fondos_insuficientes $end
$var wire 1 % pin_incorrecto $end
$var reg 1 - clk $end
$var reg 5 : digito [4:0] $end
$var reg 1 + digito_stb $end
$var reg 32 ; monto [31:0] $end
$var reg 1 ' monto_stb $end
$var reg 16 < pin [15:0] $end
$var reg 1 $ reset $end
$var reg 1 # tarjeta_recibida $end
$var reg 1 " tipo_de_tarjeta $end
$var reg 1 ! tipo_trans $end
$upscope $end
$upscope $end
$enddefinitions $end
#0
$dumpvars
b0 <
b0 ;
b0 :
bx 9
bx 8
b0 7
bx 6
bx 5
bx 4
b0 3
b0 2
b0 1
x0
x/
x.
0-
b0 ,
x+
x*
x)
b0 (
0'
b0 &
x%
1$
0#
x"
0!
$end
#1
b0 4
b0 9
1-
#2
b1 7
b0 6
b0 8
b0 5
00
0.
0%
0)
0*
0/
b11010001000011 &
b11010001000011 1
b11010001000011 <
0"
1#
0$
0-
#3
b0 7
1-
#4
0-
#5
b0 7
1-
b11 ,
b11 3
b11 :
#6
b1 7
0-
1+
#7
b0 7
1-
b0 ,
b0 3
b0 :
0+
#8
0-
#9
1-
#10
b1 7
0-
b100 ,
b100 3
b100 :
#11
b0 7
1-
1+
#12
b1 7
0-
b0 ,
b0 3
b0 :
0+
#13
b0 7
1-
#14
0-
#15
b0 7
1-
b100 ,
b100 3
b100 :
#16
b1 7
0-
1+
#17
b0 7
1-
b0 ,
b0 3
b0 :
0+
#18
0-
#19
1-
#20
b1 7
0-
b11 ,
b11 3
b11 :
#21
b0 7
1-
1+
#22
b1 7
0-
b0 ,
b0 3
b0 :
0+
#23
b0 7
1-
#24
0-
#25
b0 7
1-
b1100100 (
b1100100 2
b1100100 ;
#26
b1 7
0-
1'
#27
b0 7
1-
b0 (
b0 2
b0 ;
0'
