codigo_2/tester.v
// Actual test code for the adder module
module tester
	    (
	    CLK,
	    RESET,
	    TARJETA_RECIBIDA,
		TIPO_DE_TARJETA,
	    PIN,
	    DIGITO,
	    DIGITO_STB,
	    TIPO_TRANS,
	    MONTO,
	    MONTO_STB,
	    BALANCE_ACTUALIZADO,
	    ENTREGAR_DINERO,
	    FONDOS_INSUFICIENTES,
	    PIN_INCORRECTO,
	    ADVERTENCIA,
	    BLOQUEO
	    );



// Para el tester, se invierten las entradas y salidas respecto al DUT,
// esto para manipular el módulo que se estudia
// Declaración de entradas
input	// Todas las salidas son binarias
	BALANCE_ACTUALIZADO,
	ENTREGAR_DINERO,
	FONDOS_INSUFICIENTES,
	PIN_INCORRECTO,
	ADVERTENCIA,
	BLOQUEO;

// Declaración de salidas
output
	CLK,
	RESET,
	TARJETA_RECIBIDA,
	TIPO_DE_TARJETA,
	DIGITO_STB,
	TIPO_TRANS,
	MONTO_STB;
output [15:0] PIN;
output [3:0] DIGITO;
output [31:0] MONTO;

// Los roles de las señales también se invierten
// Declaración de roles para entradas
wire
	BALANCE_ACTUALIZADO,
	ENTREGAR_DINERO,
	FONDOS_INSUFICIENTES,
	PIN_INCORRECTO,
	ADVERTENCIA,
	BLOQUEO;

// Declaración de roles para salidas
reg
	CLK,
	RESET,
	TARJETA_RECIBIDA,
	TIPO_DE_TARJETA,
	DIGITO_STB,	// Será 1 cada vez que se ingrese el monto
	TIPO_TRANS,
	MONTO_STB;	// Será 1 cada vez que se ingrese un dígito
reg [15:0] PIN;	// Pin correcto dado por la tarjeta
reg [3:0] DIGITO;	// La entrada de dígito es volátil
reg [31:0] MONTO;	// Cantidad a operar en la transacción

// Definición de media frecuencia, en términos de unidades de tiempo
parameter h_freq=1;

// Señal de reloj
always begin
	#h_freq CLK = !CLK;
end

// Código de las pruebas
initial begin
	#0 CLK			=	0;
	#0 RESET		=	1;
	#0 TARJETA_RECIBIDA	=	0;
	#0 TIPO_DE_TARJETA = 0;
	#0 DIGITO_STB		=	0;
	#0 TIPO_TRANS		=	0;
	#0 MONTO_STB		=	0;
	#0 PIN			=	15'b0;
	#0 DIGITO		=	3'b0;
	#0 MONTO		=	31'b0;
	// Inicialización del cajero automático
	#1 RESET		=	0;
	#1 RESET		=	1;
	   TARJETA_RECIBIDA	=	1;
	   TIPO_DE_TARJETA = 1; //se va a probar el caso 1 primero (una tarjeta de un banco ajeno)
	   PIN			=	'h3443; //cambiar el pin luego

// Caso 1: tarjeta recibida + depósito:
	// 	en este caso se trabaja con una tarjeta de un banco ajeno
	// A.1:
	// 	Ingreso del pin
	
	// 	Primer dígito
	#3 DIGITO		=	3;
	#1 DIGITO_STB		=	1;
	#1 DIGITO_STB		=	0;
	   DIGITO		=	0;

	// 	Segundo dígito
	#3 DIGITO		=	4;
	#1 DIGITO_STB		=	1;
	#1 DIGITO_STB		=	0;
	   DIGITO		=	0;

	// 	Tercer dígito
	#3 DIGITO		=	4;
	#1 DIGITO_STB		=	1;
	#1 DIGITO_STB		=	0;
	   DIGITO		=	0;

	// 	Cuarto dígito
	#3 DIGITO		=	3;
	#1 DIGITO_STB		=	1;
	#1 DIGITO_STB		=	0;
	   DIGITO		=	0;
	//se autentica el usuario

	//se realiza el depósito
	   TIPO_TRANS		=	0;

	// 	Se ingresa el monto a depositar
	#3 MONTO		=	1000000000;
	#1 MONTO_STB		=	1;
	#1 MONTO_STB		=	0;
	   MONTO		=	0;
	// Depósito exitoso	

	//Finalmente, se resetea el cajero
	#0 TIPO_DE_TARJETA	=	0;
	#5 RESET = 0;
	#5 RESET = 1;

	#50;

	#0 TARJETA_RECIBIDA	=	0;
	#0 TIPO_DE_TARJETA = 0;
	#0 DIGITO_STB		=	0;
	#0 TIPO_TRANS		=	0;
	#0 MONTO_STB		=	0;
	#0 PIN			=	15'b0;
	#0 DIGITO		=	3'b0;
	#0 MONTO		=	31'b0;
	// Inicialización del cajero automático
	#1 RESET		=	0;
	#1 RESET		=	1;
	TARJETA_RECIBIDA	=	1;
    TIPO_DE_TARJETA = 0; //se va a probar el caso 1 primero (una tarjeta de un banco ajeno)
    PIN			=	'h3443; //cambiar el pin luego

	//Caso 2: pin acertado + retiro:
	//es exactamente igual al caso 1, solo que en vez de deposito es retiro.
	//primero se prueba con fondos insuficientes
	// 	Ingreso del pin
	// 	Primer dígito
	#3 DIGITO		=	3;
	#1 DIGITO_STB		=	1;
	#1 DIGITO_STB		=	0;
	   DIGITO		=	0;

	// 	Segundo dígito
	#3 DIGITO		=	4;
	#1 DIGITO_STB		=	1;
	#1 DIGITO_STB		=	0;
	   DIGITO		=	0;

	// 	Tercer dígito
	#3 DIGITO		=	4;
	#1 DIGITO_STB		=	1;
	#1 DIGITO_STB		=	0;
	   DIGITO		=	0;

	// 	Cuarto dígito
	#3 DIGITO		=	3;
	#1 DIGITO_STB		=	1;
	#1 DIGITO_STB		=	0;
	   DIGITO		=	0;
	//se autentica el usuario
	//retiro con fondos insuficientes
	#3 MONTO = 1000000000000000;
	#1 MONTO_STB = 1;
	#1 MONTO_STB = 0;
		MONTO = 0;

	//se vuelve a ingresar el pin y se realiza
	#5 TIPO_TRANS = 1;
	#5 RESET = 0;
	#5 RESET = 1;

	//se ingresa el pin
	// 	Primer dígito
	#3 DIGITO		=	3;
	#1 DIGITO_STB		=	1;
	#1 DIGITO_STB		=	0;
	   DIGITO		=	0;

	// 	Segundo dígito
	#3 DIGITO		=	4;
	#1 DIGITO_STB		=	1;
	#1 DIGITO_STB		=	0;
	   DIGITO		=	0;

	// 	Tercer dígito
	#3 DIGITO		=	4;
	#1 DIGITO_STB		=	1;
	#1 DIGITO_STB		=	0;
	   DIGITO		=	0;

	// 	Cuarto dígito
	#3 DIGITO		=	3;
	#1 DIGITO_STB		=	1;
	#1 DIGITO_STB		=	0;
	   DIGITO		=	0;
	// se autentica el usuario
	//se procede a realizar el retiro con suficientes fondos
	#3 MONTO = 9100;
	#1 MONTO_STB = 1;
	#1 MONTO_STB = 0;
		MONTO = 0;

	// Caso 3: tarjeta recibida + pin incorrecto:
	// en este caso se trabaja con una tarjeta de un banco ajeno
	// A.1:
	// Ingreso del pin
	
	// Intento 1
	// 	Primer dígito
	#3 DIGITO		=	9;
	#1 DIGITO_STB		=	1;
	#1 DIGITO_STB		=	0;
	   DIGITO		=	0;

	// 	Segundo dígito
	#3 DIGITO		=	8;
	#1 DIGITO_STB		=	1;
	#1 DIGITO_STB		=	0;
	   DIGITO		=	0;

	// 	Tercer dígito
	#3 DIGITO		=	9;
	#1 DIGITO_STB		=	1;
	#1 DIGITO_STB		=	0;
	   DIGITO		=	0;

	// 	Cuarto dígito
	#3 DIGITO		=	8;
	#1 DIGITO_STB		=	1;
	#1 DIGITO_STB		=	0;
	   DIGITO		=	0;


	// Intento 2
// 	Primer dígito
	#3 DIGITO		=	5;
	#1 DIGITO_STB		=	1;
	#1 DIGITO_STB		=	0;
	   DIGITO		=	0;

	// 	Segundo dígito
	#3 DIGITO		=	8;
	#1 DIGITO_STB		=	1;
	#1 DIGITO_STB		=	0;
	   DIGITO		=	0;

	// 	Tercer dígito
	#3 DIGITO		=	7;
	#1 DIGITO_STB		=	1;
	#1 DIGITO_STB		=	0;
	   DIGITO		=	0;

	// 	Cuarto dígito
	#3 DIGITO		=	0;
	#1 DIGITO_STB		=	1;
	#1 DIGITO_STB		=	0;
	   DIGITO		=	0;

	// Intento 3
	// 	Primer dígito
	#3 DIGITO		=	4;
	#1 DIGITO_STB		=	1;
	#1 DIGITO_STB		=	0;
	   DIGITO		=	0;

	// 	Segundo dígito
	#3 DIGITO		=	7;
	#1 DIGITO_STB		=	1;
	#1 DIGITO_STB		=	0;
	   DIGITO		=	0;

	// 	Tercer dígito
	#3 DIGITO		=	3;
	#1 DIGITO_STB		=	1;
	#1 DIGITO_STB		=	0;
	   DIGITO		=	0;

	// 	Cuarto dígito
	#3 DIGITO		=	8;
	#1 DIGITO_STB		=	1;
	#1 DIGITO_STB		=	0;
	   DIGITO		=	0;

	#10 $finish;
end


endmodule

codigo_2/atm_fsm.v
// Declaración del módulo y parámetros
module atm //#()
	    (    
	    CLK,
	    RESET,
	    TARJETA_RECIBIDA,
		TIPO_DE_TARJETA,
	    PIN,
	    DIGITO,
	    DIGITO_STB,
	    TIPO_TRANS,
	    MONTO,
	    MONTO_STB,
	    BALANCE_ACTUALIZADO,
	    ENTREGAR_DINERO,
	    FONDOS_INSUFICIENTES,
	    PIN_INCORRECTO,
	    ADVERTENCIA,
	    BLOQUEO
    	    );

// Declaración de entradas y salidas
input
	CLK,
	RESET,
	TARJETA_RECIBIDA,
	TIPO_DE_TARJETA,
	DIGITO_STB,
	TIPO_TRANS,
	MONTO_STB;
input [15:0] PIN;
input [3:0] DIGITO;
input [31:0] MONTO;

output	reg // Todas las salidas son binarias
	BALANCE_ACTUALIZADO,
	ENTREGAR_DINERO,
	FONDOS_INSUFICIENTES,
	PIN_INCORRECTO,
	ADVERTENCIA,
	BLOQUEO;

// Declaración de roles para entradas
wire
	CLK,
	RESET,
	TARJETA_RECIBIDA,
	TIPO_DE_TARJETA,
	DIGITO_STB,	// Será 1 cada vez que se ingrese el monto
	TIPO_TRANS,
	MONTO_STB;	// Será 1 cada vez que se ingrese un dígito
wire [15:0] PIN;	// Pin correcto dado por la tarjeta
wire [3:0] DIGITO;	// La entrada de dígito es volátil
wire [31:0] MONTO;	// Cantidad a operar en la transacción




// Declaración de variables internas
reg [63:0] BALANCE;	// Dinero en la cuenta
reg [1:0] Intentos_PIN;	// Contador de intentos fallidos para verificar la tarjeta
reg [2:0] Contador_PIN;	// Contador de dígitos del pin ingresados al sistema
reg [15:0] PIN_usuario;	// Ping tentativo que digita el usuario

// Declaración de vectores de estados
reg [5:0] estado_actual;
reg [5:0] prox_estado;

// Definir todos los flip flops
// Se encarga de pasar del estado actual al estado siguiente
always @(posedge CLK) begin
	// La señal de reinicio funciona invertida, si RESET == 1,
	// el cajero funciona bien, caso contrario pasa al estado
	// 6'b000001
	if (~RESET) begin
		estado_actual	<=	6'b000001;
		BALANCE_ACTUALIZADO <= 0;

	end else begin
		estado_actual  	<=	prox_estado;
	end
end



// Lógica combinacional que se encarga
// de la transición de estados
// El bloque crea flip flops, se usan
// asignaciones no bloqueantes, salvo
// para prox_estado porque esa señal
// se actualiza cada ciclo de reloj
// y ahí se usan asignaciones no 
// bloqueantes
always @(*) begin
	case (estado_actual)
		// Estado 0: Esperando tarjeta
		6'b000001:
		begin
			// Se evalúa si se ingresó la tarjeta para pasar
			// o no de estado
			if (TARJETA_RECIBIDA == 1 && TIPO_DE_TARJETA == 0) begin
				// Se ingresa una tarjeta y esta es del bcr
				BALANCE_ACTUALIZADO	=	0;
				ENTREGAR_DINERO		=	0;
				FONDOS_INSUFICIENTES	=	0;
				PIN_INCORRECTO		=	0;
				ADVERTENCIA		=	0;
				BLOQUEO			=	0;
				PIN_usuario		=	0;
				Contador_PIN		=	3'b0;
				Intentos_PIN		=	2'b00;
				// Finalmente, se pasa al estado
				prox_estado	=	6'b000010;

			end else if (TARJETA_RECIBIDA == 1 && TIPO_DE_TARJETA == 1)begin
				// Se recibe una tarjeta de otro banco
				//BALANCE_ACTUALIZADO	=	0;
				ENTREGAR_DINERO		=	0;
				FONDOS_INSUFICIENTES	=	0;
				PIN_INCORRECTO		=	0;
				ADVERTENCIA		=	0;
				BLOQUEO			=	0;
				PIN_usuario		=	0;
				Contador_PIN		=  3'b0;
				Intentos_PIN		=	2'b00;
				//se cobra la comisión
				BALANCE = BALANCE - 2;
				BALANCE_ACTUALIZADO = 1;
				//se pasa al próximo estado
				prox_estado = 6'b000010;
				//prox_estado	=	6'b000001;
				//BALANCE		<=	'0;
			end else begin
				//no hay tarjeta y se queda esperando que se ingrese una
				prox_estado	=	6'b000001;
				BALANCE		=	0;
				BALANCE_ACTUALIZADO = 0;
			end
		end

		// Estado 1: Esperando PIN, se encarga de esperar a que se
		// ingrese el PIN dígito a dígito, después verifica si la
		// entrada del usuario corresponde con el dato dado por la
		// tarjeta, si es correcto pasa a autenticar el usuario, si
		// falla, aumenta el número de intentos y penaliza según se
		// requiera

		6'b000010:
		begin

			// Se empieza por ingresar el PIN dígito a dígito
			PIN_INCORRECTO = 0;
			ADVERTENCIA = 0;
			BALANCE_ACTUALIZADO = 0;
			if (DIGITO_STB) begin
				// Se concatenan los últimos dígitos del PIN
				PIN_usuario = {PIN_usuario, DIGITO}; 
				Contador_PIN = Contador_PIN + 1; // Contador_PIN++
				// Una vez ingresado el pin, se asigna el
				// estado actual a volver a ingresar el pin,
				// así, si se ya se han introducido
				// suficientes dígitos, se verificará la
				// entrada, y si no, los if restantes no se
				// activarán y de volverá a esperar el
				// siguiente dígito
				prox_estado = 6'b000010;
			end else begin
				// Mientras DIGITO_STB esté en cero, se
				// mantiene esperando el ingreso
				
				if (Intentos_PIN == 3) begin
					prox_estado = 6'b000100;
				end else prox_estado = 6'b000010;
			end
			
			// Se verifica si la cantidad de dígitos ingresados es
			// 4
			if (Contador_PIN == 4) begin
				// Si hay 4 dígitos, se pasa a verificar si es
				// válido o no
				if (PIN_usuario == PIN) begin
					// Se borra el pin ingresado
					PIN_usuario = 0;
					Contador_PIN = 0; // Reinicia el contador
					prox_estado = 6'b001000;
				end else begin
					Contador_PIN = 0; // Reinicia el contador
					Intentos_PIN = Intentos_PIN + 1;
					PIN_INCORRECTO = 1;
					// No es necesario reiniciar el pin
					// porque el contador de dígitos
					// ingresados vuelve a cero, así que
					// necesariamente se necesitan 4 bits
					// nuevos para volver a comprobar.
					// Ahora, por tener de redundancia 
					// se puede agregar también
					if (Intentos_PIN < 2) begin
						prox_estado = 6'b000010;
					end

					if (Intentos_PIN == 2) begin
						ADVERTENCIA = 1;
						prox_estado = 6'b000010;
					end else if (Intentos_PIN == 3) begin
						prox_estado = 6'b000100;
					end 
				end
			end else begin
				// Si hay menos de 4 dígitos ingresados, se
				// mantiene esperando los demás
				prox_estado = prox_estado;
			end
		end
		// Estado 2: Bloqueado
		6'b000100:
		begin
			// Cuando se bloquea,se mantiene bloqueado
			BLOQUEO = 1;
			prox_estado = 6'b000100;
		end
		// Estado 3: Usuario identificado
		6'b001000:
		begin
			BALANCE_ACTUALIZADO = 0;
			// Con el usuario identificado, se pasa a esperar qué
			// tipo de transacción se desea y se pasa a ella
			if (TIPO_TRANS) begin
				// Se pasa a retiro cuando se ingresa un 1
				prox_estado = 6'b010000;
			end else begin
				// Si se ingresa un 0, se pasa a depósito
				prox_estado = 6'b100000;
			end

		end
		// Estado 4: Retiro: retira dinero del balance, verifica si el
		// monto ingresado es menor al balance de la cuenta
		6'b010000:
		begin
			BALANCE_ACTUALIZADO = 0;
			// Espera a que se digite el monto para realizar la
			// transacción
			if (MONTO_STB) begin
				if (BALANCE > MONTO) begin
					// Si es posible retirar la cantidad
					// solicitada, se procede con la
					// transacción
					BALANCE = BALANCE + -MONTO;
					BALANCE_ACTUALIZADO = 1;
					ENTREGAR_DINERO = 1;
					// Al final, se vuelve a esperar que se
					// ingrese el pin
					prox_estado = 6'b000001;
				end else begin
					// Si no hay suficientes fondos en la
					// cuenta, se indica que no los hay
					// y se vuelve a esperar el ingreso
					// del pin
					FONDOS_INSUFICIENTES = 1;
					prox_estado = 6'b000001;
				end
			end 
		end
		// Estado 5: Depósito: ingresa dinero al balance
		6'b100000:
		begin
			// Espera a que se digite el monto para realizar la
			// transacción
			BALANCE_ACTUALIZADO = 0;
			if (MONTO_STB) begin
				BALANCE = BALANCE + MONTO;
				BALANCE_ACTUALIZADO = 1;
				// Al final, se vuelve a esperar que se
				// ingrese el pin
				prox_estado = 6'b000001;
			end
		end

		default:
		begin 
			prox_estado = 6'b000001;
		end
	endcase
end

endmodule

codigo_2/testbench.v
`include "atm_fsm.v"
`include "tester.v"

// Testbench del cajero automático
module atm_fsm_tb;

// Todas las señales se declaran como wire, esto porque ya se han
// declarado como reg en los demás archivos, y este sólo
// los interconecta
wire	
	CLK,
	RESET,
	TARJETA_RECIBIDA,
	TIPO_DE_TARJETA,
	DIGITO_STB,
	TIPO_TRANS,
	MONTO_STB,
	BALANCE_ACTUALIZADO,
	ENTREGAR_DINERO,
	FONDOS_INSUFICIENTES,
	PIN_INCORRECTO,
	ADVERTENCIA,
	BLOQUEO;
wire [15:0] PIN;
wire [3:0] DIGITO;
wire [31:0] MONTO;

// Código de monitoreo
initial begin
	$dumpfile("atm_fsm_output.vcd");
	$dumpvars(-1);
	$monitor($time,,
		"CLK = %b   RESET = %b    TARJETA_RECIBIDA = %b    TIPO_DE_TARJETA = %b    PIN = %b    DIGITO = %b    DIGITO_STB = %b    TIPO_TRANS = %b    MONTO = %b    MONTO_STB = %b        BALANCE_ACTUALIZADO = %b    ENTREGAR_DINERO = %b    FONDOS_INSUFICIENTES = %b    PIN_INCORRECTO = %b    ADVERTENCIA = %b    BLOQUEO = %b", CLK, RESET, TARJETA_RECIBIDA, TIPO_DE_TARJETA, PIN, DIGITO, DIGITO_STB, TIPO_TRANS, MONTO, MONTO_STB, BALANCE_ACTUALIZADO, ENTREGAR_DINERO, FONDOS_INSUFICIENTES, PIN_INCORRECTO, ADVERTENCIA, BLOQUEO);
end


// Instance creation for DUT and tester modules
atm A0 (
	.CLK (CLK),
	.RESET (RESET),
	.TARJETA_RECIBIDA (TARJETA_RECIBIDA),
	.TIPO_DE_TARJETA(TIPO_DE_TARJETA),
	.PIN (PIN),
	.DIGITO (DIGITO),
	.DIGITO_STB (DIGITO_STB),
	.TIPO_TRANS (TIPO_TRANS),
	.MONTO (MONTO),
	.MONTO_STB (MONTO_STB),
	.BALANCE_ACTUALIZADO (BALANCE_ACTUALIZADO),
	.ENTREGAR_DINERO (ENTREGAR_DINERO),
	.FONDOS_INSUFICIENTES (FONDOS_INSUFICIENTES),
	.PIN_INCORRECTO (PIN_INCORRECTO),
	.ADVERTENCIA (ADVERTENCIA),
	.BLOQUEO (BLOQUEO)
);

tester P0 (
	.CLK (CLK),
	.RESET (RESET),
	.TARJETA_RECIBIDA (TARJETA_RECIBIDA),
	.TIPO_DE_TARJETA(TIPO_DE_TARJETA),
	.PIN (PIN),
	.DIGITO (DIGITO),
	.DIGITO_STB (DIGITO_STB),
	.TIPO_TRANS (TIPO_TRANS),
	.MONTO (MONTO),
	.MONTO_STB (MONTO_STB),
	.BALANCE_ACTUALIZADO (BALANCE_ACTUALIZADO),
	.ENTREGAR_DINERO (ENTREGAR_DINERO),
	.FONDOS_INSUFICIENTES (FONDOS_INSUFICIENTES),
	.PIN_INCORRECTO (PIN_INCORRECTO),
	.ADVERTENCIA (ADVERTENCIA),
	.BLOQUEO (BLOQUEO)
);

endmodule

codigo_2/atm_fsm_output.vcd
$date
	Fri May 17 14:29:07 2024
$end
$version
	Icarus Verilog
$end
$timescale
	1s
$end
$scope module atm_fsm_tb $end
$var wire 1 ! TIPO_TRANS $end
$var wire 1 " TIPO_DE_TARJETA $end
$var wire 1 # TARJETA_RECIBIDA $end
$var wire 1 $ RESET $end
$var wire 1 % PIN_INCORRECTO $end
$var wire 16 & PIN [15:0] $end
$var wire 1 ' MONTO_STB $end
$var wire 32 ( MONTO [31:0] $end
$var wire 1 ) FONDOS_INSUFICIENTES $end
$var wire 1 * ENTREGAR_DINERO $end
$var wire 1 + DIGITO_STB $end
$var wire 4 , DIGITO [3:0] $end
$var wire 1 - CLK $end
$var wire 1 . BLOQUEO $end
$var wire 1 / BALANCE_ACTUALIZADO $end
$var wire 1 0 ADVERTENCIA $end
$scope module A0 $end
$var wire 1 ! TIPO_TRANS $end
$var wire 1 " TIPO_DE_TARJETA $end
$var wire 1 # TARJETA_RECIBIDA $end
$var wire 1 $ RESET $end
$var wire 16 1 PIN [15:0] $end
$var wire 1 ' MONTO_STB $end
$var wire 32 2 MONTO [31:0] $end
$var wire 1 + DIGITO_STB $end
$var wire 4 3 DIGITO [3:0] $end
$var wire 1 - CLK $end
$var reg 1 0 ADVERTENCIA $end
$var reg 64 4 BALANCE [63:0] $end
$var reg 1 / BALANCE_ACTUALIZADO $end
$var reg 1 . BLOQUEO $end
$var reg 3 5 Contador_PIN [2:0] $end
$var reg 1 * ENTREGAR_DINERO $end
$var reg 1 ) FONDOS_INSUFICIENTES $end
$var reg 2 6 Intentos_PIN [1:0] $end
$var reg 1 % PIN_INCORRECTO $end
$var reg 16 7 PIN_usuario [15:0] $end
$var reg 6 8 estado_actual [5:0] $end
$var reg 6 9 prox_estado [5:0] $end
$upscope $end
$scope module P0 $end
$var wire 1 0 ADVERTENCIA $end
$var wire 1 / BALANCE_ACTUALIZADO $end
$var wire 1 . BLOQUEO $end
$var wire 1 * ENTREGAR_DINERO $end
$var wire 1 ) FONDOS_INSUFICIENTES $end
$var wire 1 % PIN_INCORRECTO $end
$var reg 1 - CLK $end
$var reg 4 : DIGITO [3:0] $end
$var reg 1 + DIGITO_STB $end
$var reg 32 ; MONTO [31:0] $end
$var reg 1 ' MONTO_STB $end
$var reg 16 < PIN [15:0] $end
$var reg 1 $ RESET $end
$var reg 1 # TARJETA_RECIBIDA $end
$var reg 1 " TIPO_DE_TARJETA $end
$var reg 1 ! TIPO_TRANS $end
$upscope $end
$upscope $end
$enddefinitions $end
#0
$dumpvars
b0 <
b0 ;
b0 :
b1 9
bx 8
bx 7
bx 6
bx 5
bx 4
b0 3
b0 2
b0 1
x0
x/
x.
0-
b0 ,
0+
x*
x)
b0 (
0'
b0 &
x%
1$
0#
0"
0!
$end
#1
b0 4
0/
b1 8
0$
1-
#2
b10 9
1/
b1111111111111111111111111111111111111111111111111111111111111110 4
b0 6
b0 5
b0 7
0.
00
0%
0)
0*
b11010001000011 &
b11010001000011 1
b11010001000011 <
1"
1#
1$
0-
#3
0/
b10 8
1-
#4
0-
#5
1-
b11 ,
b11 3
b11 :
#6
b1 5
b11 7
0-
1+
#7
1-
b0 ,
b0 3
b0 :
0+
#8
0-
#9
1-
#10
0-
b100 ,
b100 3
b100 :
#11
b10 5
b110100 7
1-
1+
#12
0-
b0 ,
b0 3
b0 :
0+
#13
1-
#14
0-
#15
1-
b100 ,
b100 3
b100 :
#16
b11 5
b1101000100 7
0-
1+
#17
1-
b0 ,
b0 3
b0 :
0+
#18
0-
#19
1-
#20
0-
b11 ,
b11 3
b11 :
#21
b1000 8
b100000 9
b0 5
b0 7
1-
1+
#22
0-
b0 ,
b0 3
b0 :
0+
#23
b100000 8
1-
#24
0-
#25
1-
b111011100110101100101000000000 (
b111011100110101100101000000000 2
b111011100110101100101000000000 ;
#26
b1 9
1/
b111011100110101100100111111110 4
0-
1'
#27
b10 9
b1 8
0"
0/
1-
b0 (
b0 2
b0 ;
0'
#28
0-
#29
b10 8
1-
#30
0-
#31
1-
#32
0-
0$
#33
b1 8
1-
#34
0-
#35
1-
#36
0-
#37
b10 8
1-
1$
